{"locations":{"Medical Bay":{"npc":"visitor","zombie":null,"itemList":["health kit","lever"]},"Landing Dock":{"npc":"guard","zombie":null,"itemList":[]},"Bar":{"npc":null,"zombie":null,"itemList":["swiss army knife"]},"Escape Shuttle":{"npc":null,"zombie":null,"itemList":["oxygen tank"]},"Central Hub":{"npc":null,"zombie":null,"itemList":["zombie katana","zombie armor"]},"Ship":{"npc":null,"zombie":null,"itemList":[]},"Repair Workshop":{"npc":"engineer","zombie":null,"itemList":["wizzlewhat","space wrench"]}},"player":{"health":3,"inventory":[],"currentLocation":"Landing Dock"}}